{
    "KPlugin": {
        "Authors": [
            {
                "Email": "ramin.gomari@gmail.com",
                "Name": "Ramin Gomari",
                "Name[ca@valencia]": "Ramin Gomari",
                "Name[ca]": "Ramin Gomari",
                "Name[en_GB]": "Ramin Gomari",
                "Name[es]": "Ramin Gomari",
                "Name[fr]": "Ramin Gomari",
                "Name[it]": "Ramin Gomari",
                "Name[ka]": "Ramin Gomari",
                "Name[nl]": "Ramin Gomari",
                "Name[pl]": "Ramin Gomari",
                "Name[pt]": "Ramin Gomari",
                "Name[sl]": "Ramin Gomari",
                "Name[sv]": "Ramin Gomari",
                "Name[tr]": "Ramin Gomari",
                "Name[uk]": "Ramin Gomari",
                "Name[x-test]": "xxRamin Gomarixx"
            }
        ],
        "Category": "Plugins",
        "Description": "Tells your friends what you are listening to",
        "Description[ca@valencia]": "Diu als vostres amics el què esteu escoltant",
        "Description[ca]": "Diu als vostres amics el què esteu escoltant",
        "Description[en_GB]": "Tells your friends what you are listening to",
        "Description[es]": "Comunica a tus amigos lo que estás escuchando",
        "Description[fr]": "Signale à vos personnes amies que vous écoutez.",
        "Description[it]": "Dice ai tuoi amici che cosa stai ascoltando",
        "Description[ka]": "ეტყვის თქვენს მეგობრებს, რას უსმენთ",
        "Description[nl]": "Vertelt uw vrienden waarnaar u naar luistert.",
        "Description[pt]": "Diz aos seus amigos o que está a ouvir de momento",
        "Description[sl]": "Pove svojim prijateljem, kaj poslušate",
        "Description[sv]": "Talar om för dina vänner vad du lyssnar på",
        "Description[tr]": "Arkadaşlarınıza ne dinlediğinizi söyleyin.",
        "Description[uk]": "Повідомляє вашим друзям про музику, яку ви слухаєте",
        "Description[x-test]": "xxTells your friends what you are listening toxx",
        "EnabledByDefault": true,
        "Icon": "media-playback-start",
        "Id": "choqok_nowlistening",
        "License": "GPL",
        "Name": "Now Listening",
        "Name[ca@valencia]": "Ara s'escolta",
        "Name[ca]": "Ara s'escolta",
        "Name[cs]": "Nyní poslouchám",
        "Name[en_GB]": "Now Listening",
        "Name[es]": "Escuchando ahora",
        "Name[fr]": "En écoute maintenant",
        "Name[ia]": "Ora ascoltante",
        "Name[it]": "In ascolto",
        "Name[ka]": "ახლა უსმენთ",
        "Name[nl]": "Luistert nu naar",
        "Name[pl]": "Teraz odsłuchiwane",
        "Name[pt]": "Agora a Ouvir",
        "Name[sl]": "Zdaj poslušanje",
        "Name[sv]": "Lyssnar nu",
        "Name[tr]": "Şimdi Dinleniyor",
        "Name[uk]": "Зараз слухаю",
        "Name[x-test]": "xxNow Listeningxx",
        "Version": "0.5",
        "Website": "https://choqok.kde.org"
    },
    "X-KDE-ConfigModule": "choqok_plugins/kcms/kcm_choqok_nowlistening"
}
